datadownunder/__init__.py
datadownunder-0.1.dist-info/LICENSE
datadownunder-0.1.dist-info/METADATA
datadownunder-0.1.dist-info/WHEEL
datadownunder-0.1.dist-info/top_level.txt
datadownunder-0.1.dist-info/RECORD
