Metadata-Version: 2.1
Name: datadownunder
Version: 0.1
Summary: A python package to download from datagovau
Home-page: https://github.com/uaineteine/datadownunder
Author: Daniel Stamer-Squair
Author-email: uaine.teine@hotmail.com
Classifier: Programming Language :: Python :: 3
Classifier: License :: OSI Approved :: GNU General Public License v3 (GPLv3)
Classifier: Operating System :: OS Independent
Requires-Python: >=3.9
License-File: LICENSE
Requires-Dist: requests
Requires-Dist: tqdm
Requires-Dist: uainepydat
